setup.py
nyancat/__init__.py
nyancat/frame.py
nyancat/nyancat.py
nyancat.egg-info/PKG-INFO
nyancat.egg-info/SOURCES.txt
nyancat.egg-info/dependency_links.txt
nyancat.egg-info/entry_points.txt
nyancat.egg-info/pbr.json
nyancat.egg-info/top_level.txt
nyancat.egg-info/zip-safe