Metadata-Version: 1.0
Name: nyancat
Version: 0.1.2
Summary: nyancat in your terminal based on Python!
Home-page: https://github.com/taizilongxu/nyancat
Author: taizilongxu
Author-email: 468137306@qq.com
License: MIT
Keywords: python nyancat terminal
Platform: UNKNOWN
